{
  "helps": [
    {
      "name": "Олександр Попик",
      "position": "qweqw",
      "city": "Paris",
      "email": "Theosenigma@gmail.com",
      "phone": "0959083960",
      "id": 1
    },
    {
      "name": "Олександр Попик",
      "position": "qweqw",
      "city": "Paris",
      "email": "theosenigma@gmail.com",
      "phone": "0959083960",
      "id": 2
    },
    {
      "name": "Олександр Попик",
      "position": "qweqw",
      "city": "London",
      "email": "theosenigma@gmail.com",
      "phone": "0959083960",
      "id": 3
    },
    {
      "name": "Олександр Попик",
      "position": "",
      "city": "New-York",
      "email": "",
      "phone": "0959083960",
      "id": 4
    },
    {
      "name": "Олександр Попик",
      "position": "",
      "city": "New-York",
      "email": "",
      "phone": "0959083960",
      "id": 5
    },
    {
      "name": "Олександр Попик",
      "position": "",
      "city": "New-York",
      "email": "",
      "phone": "0959083960",
      "id": 6
    },
    {
      "name": "",
      "position": "",
      "city": "New-York",
      "email": "",
      "phone": "",
      "id": 7
    },
    {
      "name": "Олександр Попик",
      "position": "",
      "city": "New-York",
      "email": "",
      "phone": "0959083960",
      "id": 8
    },
    {
      "name": "",
      "position": "",
      "city": "New-York",
      "email": "",
      "phone": "",
      "id": 9
    },
    {
      "name": "",
      "position": "",
      "city": "New-York",
      "email": "",
      "phone": "",
      "id": 10
    },
    {
      "name": "",
      "position": "",
      "city": "New-York",
      "email": "",
      "phone": "",
      "id": 11
    },
    {
      "name": "",
      "position": "",
      "city": "New-York",
      "email": "",
      "phone": "",
      "id": 12
    },
    {
      "name": "Олександр Попик",
      "position": "",
      "city": "New-York",
      "email": "",
      "phone": "0959083960",
      "id": 13
    },
    {
      "name": "Олександр Попик",
      "position": "",
      "city": "New-York",
      "email": "",
      "phone": "0959083960",
      "id": 14
    },
    {
      "name": "Олександр Попик",
      "position": "",
      "city": "New-York",
      "email": "",
      "phone": "0959083960",
      "id": 15
    },
    {
      "name": "",
      "position": "",
      "city": "New-York",
      "email": "",
      "phone": "",
      "id": 16
    },
    {
      "name": "",
      "position": "",
      "city": "New-York",
      "email": "",
      "phone": "",
      "id": 17
    },
    {
      "name": "",
      "position": "",
      "city": "New-York",
      "email": "",
      "phone": "",
      "id": 18
    },
    {
      "name": "",
      "position": "",
      "city": "New-York",
      "email": "",
      "phone": "",
      "id": 19
    },
    {
      "name": "",
      "position": "",
      "city": "New-York",
      "email": "",
      "phone": "",
      "id": 20
    },
    {
      "name": "",
      "position": "",
      "city": "New-York",
      "email": "",
      "phone": "",
      "id": 21
    }
  ],
  "schedule": [
    {
      "name": "Олександр",
      "email": "popukpetro@gmail.com",
      "date": "0002-04-03",
      "id": 1
    },
    {
      "name": "",
      "email": "",
      "date": "",
      "id": 2
    },
    {
      "name": "",
      "email": "",
      "date": "",
      "id": 3
    },
    {
      "name": "Олександр",
      "email": "popukpetro@gmail.com",
      "date": "",
      "id": 4
    },
    {
      "name": "",
      "email": "",
      "date": "",
      "id": 5
    },
    {
      "name": "",
      "email": "",
      "date": "",
      "id": 6
    },
    {
      "name": "",
      "email": "",
      "date": "",
      "id": 7
    },
    {
      "name": "",
      "email": "",
      "date": "",
      "id": 8
    },
    {
      "name": "",
      "email": "",
      "date": "",
      "id": 9
    },
    {
      "name": "",
      "email": "",
      "date": "",
      "id": 10
    },
    {
      "name": "",
      "email": "",
      "date": "",
      "id": 11
    },
    {
      "name": "",
      "email": "",
      "date": "",
      "id": 12
    },
    {
      "name": "",
      "email": "",
      "date": "",
      "id": 13
    },
    {
      "name": "",
      "email": "",
      "date": "",
      "id": 14
    },
    {
      "name": "",
      "email": "",
      "date": "",
      "id": 15
    }
  ]
}